README.md
setup.cfg
setup.py
src/HubLatest.egg-info/PKG-INFO
src/HubLatest.egg-info/SOURCES.txt
src/HubLatest.egg-info/dependency_links.txt
src/HubLatest.egg-info/entry_points.txt
src/HubLatest.egg-info/requires.txt
src/HubLatest.egg-info/top_level.txt
src/hublatest/__init__.py
src/hublatest/__main__.py
src/hublatest/file_download.py
src/hublatest/hublatest.py
src/hublatest.egg-info/PKG-INFO
src/hublatest.egg-info/SOURCES.txt
src/hublatest.egg-info/dependency_links.txt
src/hublatest.egg-info/entry_points.txt
src/hublatest.egg-info/top_level.txt
src/hublatest/locale/zh_CN/LC_MESSAGES/messages.mo