Metadata-Version: 2.1
Name: HubLatest
Version: 0.1.3
Summary: Script to automatically download latest release from GitHub repos
Home-page: https://github.com/Codex-in-somnio/HubLatest
Author: Codex-in-Somnio
Author-email: yyy3752@gmail.com
License: MIT
Platform: UNKNOWN
Classifier: Development Status :: 4 - Beta
Classifier: Environment :: Console
Classifier: Intended Audience :: System Administrators
Classifier: Programming Language :: Python :: 3 :: Only
Classifier: License :: OSI Approved :: MIT License
Classifier: Operating System :: OS Independent
Classifier: Topic :: Software Development :: Version Control :: Git
Requires-Python: >=3.6
